lain_shorten/__init__.py
lain_shorten/__main__.py
lain_shorten/cli.py
lain_shorten/shorten.py
lain_shorten/version.py
lain_shorten-1.16.dist-info/licenses/LICENSE
lain_shorten-1.16.dist-info/WHEEL
lain_shorten-1.16.dist-info/entry_points.txt
lain_shorten-1.16.dist-info/METADATA
lain_shorten-1.16.dist-info/RECORD
