Metadata-Version: 2.4
Name: lain-shorten
Version: 1.16
Summary: URL Shortener using s.lain.la API.
Keywords: python,link shortener,shortener,lain,lain.la,s.lain.la,kuroneko
Author: NecRaul
Author-email: NecRaul <necraul@kuroneko.dev>
License-Expression: LGPL-2.1-only
License-File: LICENSE
Classifier: Development Status :: 5 - Production/Stable
Classifier: Environment :: Console
Classifier: Intended Audience :: Developers
Classifier: Natural Language :: English
Classifier: Operating System :: OS Independent
Classifier: Programming Language :: Python :: 3 :: Only
Classifier: Programming Language :: Python :: 3.10
Classifier: Programming Language :: Python :: 3.11
Classifier: Programming Language :: Python :: 3.12
Classifier: Programming Language :: Python :: 3.13
Classifier: Programming Language :: Python :: 3.14
Classifier: Topic :: Internet :: WWW/HTTP
Requires-Dist: requests>=2.32.5
Requires-Dist: pyperclip>=1.11.0 ; extra == 'clipboard'
Requires-Python: >=3.10
Project-URL: Homepage, https://github.com/NecRaul/lain.la-link-shortener
Project-URL: Documentation, https://github.com/NecRaul/lain.la-link-shortener#readme
Project-URL: Repository, https://github.com/NecRaul/lain.la-link-shortener
Project-URL: Issues, https://github.com/NecRaul/lain.la-link-shortener/issues
Provides-Extra: clipboard
